<item description="" manage="T" memo="" mid="54c1cce7-d7734fac" modifier="admin" mrev="1" name="fr_FR" nodepath="/SYS_Config/locale/fr_FR" objinfo="" owner="admin" pid="5ab7ff23-71e54f14" rev="1" sid="54c1cce7-d7734fac" type="PrivateContent" uid="8b666fd7-1ee8417b" updatedate="1450747690129" updatedatefm="2015.12.22 10:28:10 AM" writable="T"><li group="windows" name="T_DATA_UPLOAD"><![CDATA[Ajouter DataFile]]></li><li group="windows" name="T_DASHBOARD"><![CDATA[Tableau de bord]]></li><li group="windows" name="T_EXCEL_LOADER"><![CDATA[LocalData Loader]]></li><li group="windows" name="T_FORMULA_MEASURE"><![CDATA[Formule Mesure]]></li><li group="windows" name="T_GLOBAL_REPORT_STYLE"><![CDATA[Regarde et ressent]]></li><li group="windows" name="T_MDB_CUBE"><![CDATA[MDB Analyse acces]]></li><li group="windows" name="T_MCUBE_WINDOW"><![CDATA[m Dimension Cube]]></li><li group="windows" name="T_FILTER"><![CDATA[Filtrer les donnees]]></li><li group="windows" name="T_DYNFILTER_CONFIG"><![CDATA[Filtre Config]]></li><li group="windows" name="T_MEASURE"><![CDATA[Mesure]]></li><li group="windows" name="T_META_EDITOR"><![CDATA[Meta Editor]]></li><li group="windows" name="T_EXPORT_WIZARD"><![CDATA[Assistant Export]]></li><li group="windows" name="T_OBJECT_AUTH"><![CDATA[Objet Auth]]></li><li group="windows" name="T_UDG"><![CDATA[User Group Defini]]></li><li group="windows" name="T_PASSWORD_CHANGE"><![CDATA[Mot de passe]]></li><li group="windows" name="T_PIVOT_EDITOR"><![CDATA[Report Designer]]></li><li group="windows" name="T_CHART_WIZARD"><![CDATA[Chart Designer]]></li><li group="windows" name="T_STATISTICS"><![CDATA[Statistiques de base]]></li><li group="windows" name="T_META_IMP"><![CDATA[Chargez Meta File]]></li><li group="windows" name="T_NOSQL_CUBE"><![CDATA[BigData Analyse Cube]]></li><li group="windows" name="T_REPORT_WINDOW"><![CDATA[rapport]]></li><li group="windows" name="T_RSN"><![CDATA[Rapport sur twitter]]></li><li group="windows" name="T_CUSTOM_METRIC"><![CDATA[Metric personnalises]]></li><li group="windows" name="T_TRASHBIN"><![CDATA[Poubelle]]></li><li group="windows" name="T_CUBE_MODEL"><![CDATA[Cube Modele]]></li><li group="windows" name="T_STYLE_WIZARD"><![CDATA[Style Wizard]]></li><li group="windows" name="T_CUBE"><![CDATA[Cube]]></li><li group="windows" name="T_META_SAVE"><![CDATA[Enregistrer sous ... Item]]></li><li group="windows" name="T_META_SELECT"><![CDATA[Selectionner un article...]]></li><li group="windows" name="T_SHEET_OPTION"><![CDATA[Option de Sheet]]></li><li group="windows" name="T_BROWSER"><![CDATA[Navigateur]]></li><li group="windows" name="T_COMPOSITE_REPORT"><![CDATA[Rapport de synthese]]></li><li group="windows" name="T_TAB_BROWSER"><![CDATA[Navigateur a onglets]]></li><li group="windows" name="T_SORT_OPTION"><![CDATA[Options de tri]]></li><li group="windows" name="T_REPORT_OPTION"><![CDATA[Modifier les options de rapport]]></li><li group="sqlcube" name="I_SQLCUBE"><![CDATA[Assistant SQL]]></li><li group="sqlcube" name="I_QRY_TOOL"><![CDATA[L'editeur de requetes]]></li><li group="schedule" name="T_BG_MR"><![CDATA[Map / Reduce]]></li><li group="schedule" name="L_LST_SCH"><![CDATA[Liste de l'annexe]]></li><li group="schedule" name="T_BG_DS"><![CDATA[La source de donnees]]></li><li group="schedule" name="L_LOG_VIEW"><![CDATA[Voir le resultat de journal]]></li><li group="schedule" name="T_BG_SC"><![CDATA[Commande Shell]]></li><li group="schedule" name="T_BG_HIVEJOB"><![CDATA[Hive emploi]]></li><li group="schedule" name="L_GENERAL_OPTION"><![CDATA[Options generales]]></li><li group="schedule" name="T_BG_SCR"><![CDATA[Resultat commande]]></li><li group="schedule" name="L_RUN"><![CDATA[Courir]]></li><li group="schedule" name="B_DEFAULT"><![CDATA[Defaut]]></li><li group="schedule" name="L_REG_SCH"><![CDATA[Inscrivez annexe]]></li><li group="schedule" name="T_MANAGE"><![CDATA[Gerer]]></li><li group="schedule" name="T_BG_OP"><![CDATA[Sortie]]></li><li group="reportoptions" name="L_STACK_CHART"><![CDATA[Serie Stacked]]></li><li group="reportoptions" name="L_CHART_THEME"><![CDATA[Theme graphique]]></li><li group="reportoptions" name="L_SHOW_TITLE"><![CDATA[Afficher le titre]]></li><li group="reportoptions" name="L_RO_INST1"><![CDATA[S'il vous plait selectionner les options ci-dessus.]]></li><li group="report" name="L_CHART_TYPE"><![CDATA[Type de graphique]]></li><li group="report" name="L_VIEW_CHART"><![CDATA[Vue graphique]]></li><li group="report" name="L_LAYOUT"><![CDATA[Disposition]]></li><li group="report" name="T_LAYOUT"><![CDATA[Modeles de mise en page]]></li><li group="report" name="L_ADD_SHEET"><![CDATA[Ajouter Sheet]]></li><li group="report" name="L_LAYOUT_VERTICAL"><![CDATA[verticale]]></li><li group="report" name="L_LAYOUT_POPUP"><![CDATA[apparaitre]]></li><li group="report" name="L_EXPORT_EXCEL"><![CDATA[MS Excel]]></li><li group="report" name="L_EXPORT_PPT"><![CDATA[MS PPT]]></li><li group="report" name="L_LAYOUT_NORMAL"><![CDATA[Ordinaire]]></li><li group="report" name="T_SAVE_IMAGE"><![CDATA[image]]></li><li group="report" name="L_LAYOUT_HORIZONTAL"><![CDATA[horizontal]]></li><li group="report" name="L_SHOW_PIVOT"><![CDATA[Afficher CubeFolder]]></li><li group="report" name="L_LAYOUT_CASCADE"><![CDATA[Cascade]]></li><li group="report" name="L_VIEW_GRID"><![CDATA[Voir la feuille]]></li><li group="report" name="L_VIEW_SQL"><![CDATA[Voir SQL]]></li><li group="report" name="L_GRID_STYLE"><![CDATA[Reglez style de grille]]></li><li group="report" name="L_EXPORT"><![CDATA[Exporter]]></li><li group="report" name="L_CHANGE_REPORTTYPE"><![CDATA[Changer le type de rapport]]></li><li group="report" name="L_NO_DATA"><![CDATA[Pas de donnees]]></li><li group="report" name="L_EDIT_SQL"><![CDATA[Modifier SQL]]></li><li group="report" name="L_EXPORT_ODF_WORD"><![CDATA[Open Document]]></li><li group="report" name="L_CLIPBOARD_COPY"><![CDATA[Copier dans le presse-papier]]></li><li group="report" name="L_EXPORT_ODF_PPT"><![CDATA[Open Presentation]]></li><li group="report" name="L_EXPORT_ODF_EXCEL"><![CDATA[Ouvrir SpreadSheet]]></li><li group="report" name="L_EXPORT_OPTION"><![CDATA[Option]]></li><li group="report" name="L_EXPORT_PDF"><![CDATA[PDF]]></li><li group="report" name="L_SAVE_REPORT_AS"><![CDATA[Enregistrer en tant que rapport]]></li><li group="report" name="L_SAVE_IMAGE"><![CDATA[Enregistrer comme image]]></li><li group="report" name="L_SAVE_REPORT"><![CDATA[Enregistrer le rapport]]></li><li group="report" name="L_PIVOT_REPORT"><![CDATA[motif]]></li><li group="report" name="L_REPORT_TOOLS"><![CDATA[Rapport Outils]]></li><li group="report" name="L_R_SCRIPT"><![CDATA[R Script Editor]]></li><li group="report" name="L_VIEW_RSTAT"><![CDATA[R Statistique]]></li><li group="report" name="L_R_SUMMARY"><![CDATA[R Resume]]></li><li group="report" name="L_R_WIZARD"><![CDATA[R Assistant]]></li><li group="report" name="L_SORT_OPTION"><![CDATA[Rang et tri]]></li><li group="report" name="L_STATISTICS"><![CDATA[Statistiques de base]]></li><li group="report" name="L_RUN_REPORT"><![CDATA[Courir]]></li><li group="report" name="L_NAVIGATOR"><![CDATA[Navigateur]]></li><li group="prompt" name="T_PROMPT_DLG"><![CDATA[Rapide]]></li><li group="prompt" name="T_PROMPT_MSG"><![CDATA[Valeur pour le changement etat Remplissez]]></li><li group="pivot" name="L_AREA_ROW"><![CDATA[Rangee]]></li><li group="pivot" name="L_AREA_COLUMN"><![CDATA[Colonne]]></li><li group="pivot" name="L_PIVOT"><![CDATA[motif]]></li><li group="pivot" name="L_AREA_MEASURE"><![CDATA[Mesure]]></li><li group="nosqlcube_option" name="T_NOSQLDATA_TITLE"><![CDATA[BigData Options de connexion]]></li><li group="navmain" name="I_WIZARD"><![CDATA[Etape par etape de l'analyse]]></li><li group="navitree" name="L_RENAME_ITEM"><![CDATA[Rebaptiser @]]></li><li group="navitree" name="L_UIPAGE"><![CDATA[UI page]]></li><li group="navitree" name="L_EXCEL_LOADER"><![CDATA[Local Cube de fichier]]></li><li group="navitree" name="L_HD_BPROC"><![CDATA[BigData Conception]]></li><li group="navitree" name="L_DATE_METRIC"><![CDATA[Date de Metric]]></li><li group="navitree" name="L_SQL_CUBE"><![CDATA[SQL Cube]]></li><li group="navitree" name="L_ROLAP_CUBE_MODEL"><![CDATA[ROLAP Cube Modele]]></li><li group="navitree" name="L_ROLAP_CUBE"><![CDATA[ROLAP Cube]]></li><li group="navitree" name="L_DASHBOARD"><![CDATA[Tableau de bord]]></li><li group="navitree" name="L_FORMULA"><![CDATA[Formule]]></li><li group="navitree" name="L_MOLAP_CUBE"><![CDATA[MOLAP Cube]]></li><li group="navitree" name="L_MENU_CUBE_WORK"><![CDATA[Analyse de Cube]]></li><li group="navitree" name="L_DELETE_ITEM"><![CDATA[Effacer @]]></li><li group="navitree" name="L_NOSQL_CUBE"><![CDATA[BigData Cube]]></li><li group="navitree" name="L_DELETE_CHECKED"><![CDATA[Supprimer verifie]]></li><li group="navitree" name="L_CUSTOM_METRIC"><![CDATA[Metric personnalises]]></li><li group="navitree" name="L_MGR_FD"><![CDATA[Gerer dossier]]></li><li group="navitree" name="L_COMPOSITEREPORT"><![CDATA[Rapport de synthese]]></li><li group="navitree" name="L_MEASURE"><![CDATA[Mesure]]></li><li group="navitree" name="L_GOTO"><![CDATA[Aller a]]></li><li group="navitree" name="L_PASTE_ITEM"><![CDATA[Collez ici]]></li><li group="navitree" name="L_REPORT"><![CDATA[rapport]]></li><li group="navitree" name="L_UDG"><![CDATA[User Group Defini]]></li><li group="navitree" name="L_BROWSE_ITEM"><![CDATA[Feuilleter @]]></li><li group="navitree" name="L_METRIC"><![CDATA[Metrique]]></li><li group="navitree" name="L_EXPORT_META"><![CDATA[Exporter le contenu dans le fichier]]></li><li group="navitree" name="L_EDIT_ITEM"><![CDATA[Modifier @]]></li><li group="navitree" name="L_EMPTY_SEARCH"><![CDATA[Rechercher mot-cle]]></li><li group="navitree" name="L_VIEW_ITEM"><![CDATA[Vue @]]></li><li group="navitree" name="L_COPY_ITEM"><![CDATA[Exemplaire @]]></li><li group="navitree" name="L_CHART_MEASURE"><![CDATA[Micro Graphique]]></li><li group="navitree" name="L_OBJECT_AUTH"><![CDATA[Objet Auth]]></li><li group="navitree" name="L_MDB_CUBE"><![CDATA[MS Access Datacube]]></li><li group="navimain" name="I_DATABASE_CONNECTION"><![CDATA[Connexion de base de donnees]]></li><li group="navimain" name="I_RELATION"><![CDATA[Relation]]></li><li group="navimain" name="I_DATA"><![CDATA[DONNEES]]></li><li group="navimain" name="I_REPORT_STYLE"><![CDATA[Style Report]]></li><li group="navimain" name="I_PASSWORD"><![CDATA[Changer le mot de passe]]></li><li group="navimain" name="I_USER"><![CDATA[Utilisateur]]></li><li group="navimain" name="I_USER_MANAGER"><![CDATA[Gestionnaire des utilisateurs]]></li><li group="navimain" name="I_SYSMON"><![CDATA[Surveillance du systeme]]></li><li group="navimain" name="I_SCHEDULE"><![CDATA[Annexe surveillance]]></li><li group="navimain" name="I_TABLE_REGISTER"><![CDATA[Tableau Enregistrer]]></li><li group="navimain" name="I_HELP_MGR"><![CDATA[Gestionnaire d'aide]]></li><li group="navimain" name="I_ADMIN"><![CDATA[Administrateur]]></li><li group="navimain" name="I_META_IMP"><![CDATA[Chargez Meta File]]></li><li group="navimain" name="I_BD_CONFIG"><![CDATA[Variables]]></li><li group="navimain" name="I_ABOUT_DETAIL"><![CDATA[sur]]></li><li group="navimain" name="I_SERVER_CONFIG"><![CDATA[Config serveur]]></li><li group="navimain" name="I_ABOUT"><![CDATA[Sur @]]></li><li group="navimain" name="I_WORKSPACE"><![CDATA[Nouvel espace de travail]]></li><li group="mgrstyle" name="L_BORDER_RIGHT"><![CDATA[Droit de la frontiere]]></li><li group="mgrstyle" name="L_FONT_FACE"><![CDATA[Face Font]]></li><li group="mgrstyle" name="L_FONT_ITALIC"><![CDATA[Italique]]></li><li group="mgrstyle" name="L_PAD_BOTTOM"><![CDATA[Bas]]></li><li group="mgrstyle" name="L_PAD_RIGHT"><![CDATA[Exact]]></li><li group="mgrstyle" name="L_PAD_TOP"><![CDATA[Haut]]></li><li group="mgrstyle" name="L_PAD_LEFT"><![CDATA[Gauche]]></li><li group="mgrstyle" name="L_PADDING"><![CDATA[Rembourrage]]></li><li group="mgrstyle" name="L_STYLE_TITLE"><![CDATA[Style de titre]]></li><li group="mgrstyle" name="L_ALIGN_LEFT"><![CDATA[Gauche]]></li><li group="mgrstyle" name="L_FONT_UNDERLINE"><![CDATA[Souligner]]></li><li group="mgrstyle" name="L_STYLE_DATA"><![CDATA[Style de donnees]]></li><li group="mgrstyle" name="L_ALIGN_RIGHT"><![CDATA[Exact]]></li><li group="mgrstyle" name="L_STYLE_OPTION"><![CDATA[Option Style]]></li><li group="mgrstyle" name="L_FONT_ALIGNMENT"><![CDATA[Alignement]]></li><li group="mgrstyle" name="L_AUTO_WIDTH"><![CDATA[Taille automatique]]></li><li group="mgrstyle" name="L_BORDER_COLOR"><![CDATA[Couleur de la bordure]]></li><li group="mgrstyle" name="L_COLUMN_WIDTH"><![CDATA[Largeur de colonne]]></li><li group="mgrstyle" name="L_FONT_BOLD"><![CDATA[Audacieux]]></li><li group="mgrstyle" name="L_BORDER_BOTTOM"><![CDATA[Fond de la frontiere]]></li><li group="mgrstyle" name="L_BACK_COLOR"><![CDATA[Retour couleur]]></li><li group="mgrstyle" name="L_FORE_COLOR"><![CDATA[Couleur de premier plan]]></li><li group="mgrstyle" name="L_NULL_VALUE"><![CDATA[Valeur nulle]]></li><li group="mgrstyle" name="L_ALIGN_CENTER"><![CDATA[centre]]></li><li group="mgrstyle" name="L_FONTSIZE"><![CDATA[Taille de police]]></li><li group="mgrhelp" name="L_NEW_DOCUMENT"><![CDATA[Ajouter un document]]></li><li group="mgrhelp" name="L_KOREAN"><![CDATA[coreen]]></li><li group="mgrhelp" name="L_SELECT_LOCALE"><![CDATA[Choisir la langue]]></li><li group="mgrhelp" name="L_PREVIEW"><![CDATA[Apercu]]></li><li group="mgrhelp" name="L_ENGLISH"><![CDATA[Anglais]]></li><li group="mgrfolder" name="T_MGR_FOLDER"><![CDATA[Gestionnaire de dossiers]]></li><li group="mgrfolder" name="E_DUP_FOLDER"><![CDATA[Deplacez meme dossier est pas autorise]]></li><li group="mgrdb_template" name="T_DB_BLANK"><![CDATA[Champ requis.]]></li><li group="mgrdb_template" name="T_DB_TMPL"><![CDATA[Modele de base de donnees]]></li><li group="mgrdb" name="M_SUC_DBCON"><![CDATA[Succes pour connecter db]]></li><li group="mgrdb" name="T_DB_PWD"><![CDATA[Base de donnees de connexion]]></li><li group="mgrdb" name="M_BLANK_PWD"><![CDATA[Mot de passe ne doit pas etre vide]]></li><li group="metricsetting" name="T_METRIC_SETTING"><![CDATA[Configuration metrique]]></li><li group="mdbcube" name="L_MDB_OPTION"><![CDATA[Options de MDB]]></li><li group="mcubemain" name="L_BUILD_MCUBE"><![CDATA[Construire Cube]]></li><li group="mcubemain" name="L_LD_FILE"><![CDATA[Charge DataFile]]></li><li group="mcubemain" name="L_ADD_METRIC"><![CDATA[Ajouter nouvelle dimension]]></li><li group="mcube" name="L_LD_INI"><![CDATA[Tout effacer DataSet]]></li><li group="mcube" name="L_LD_UL"><![CDATA[Deconnectez toutes les connexions]]></li><li group="mcube" name="L_LD_LK"><![CDATA[Connectez Connexion]]></li><li group="mcube" name="L_LD_SQL"><![CDATA[SQL Query importation]]></li><li group="mcube" name="L_LD_ST"><![CDATA[modes]]></li><li group="main" name="S_NAVI"><![CDATA[Navigateur]]></li><li group="main" name="S_HOME"><![CDATA[Accueil]]></li><li group="login" name="L_BTN_LOGIN"><![CDATA[S'identifier]]></li><li group="login" name="L_INPUT_PASSWORD"><![CDATA[Mot de passe]]></li><li group="login" name="L_INPUT_USERID"><![CDATA[ID]]></li><li group="login" name="L_LOGIN_TITLE"><![CDATA[Connexion securisee]]></li><li group="locale_en_US_226" name="L_F_STR"><![CDATA[Chaine Format]]></li><li group="locale_en_US_226" name="L_FONT_ST"><![CDATA[Style de police]]></li><li group="locale_en_US_226" name="B_ST_NAME"><![CDATA[style]]></li><li group="locale_en_US_226" name="L_BG_COL"><![CDATA[Couleur de fond]]></li><li group="locale_en_US_226" name="D_JAVAPACKAGE"><![CDATA[Java Package]]></li><li group="locale_en_US_226" name="L_STACK_PERCENT"><![CDATA[Empilez par Pourcentage]]></li><li group="locale_en_US_226" name="L_C_ITEMS"><![CDATA[Sous Articles]]></li><li group="locale_en_US_226" name="M_ERROR"><![CDATA[Erreur]]></li><li group="locale_en_US_226" name="L_HL_COL"><![CDATA[Colonnes]]></li><li group="locale_en_US_226" name="L_HL_ROW"><![CDATA[Rangees]]></li><li group="locale_en_US_226" name="L_HL_CELL"><![CDATA[Seulement cellulaire]]></li><li group="locale_en_US_226" name="L_HL_DESC"><![CDATA[Cliquez sur la cellule a modifier ou cliquez sur Nouveau pour faire une nouvelle option en surbrillance.]]></li><li group="locale_en_US_226" name="L_APPL_R"><![CDATA[Appliquer sur]]></li><li group="locale_en_US_226" name="L_OPT_STYLE"><![CDATA[Option Style]]></li><li group="locale_en_US_225" name="L_F_GT_NOT"><![CDATA[Non plus alors (<=)]]></li><li group="locale_en_US_225" name="L_F_BETWEEN"><![CDATA[Entre les valeurs (ENTRE)]]></li><li group="locale_en_US_225" name="L_CLUSTER"><![CDATA[Grappe]]></li><li group="locale_en_US_225" name="L_CD_DISP_2"><![CDATA[* Faites glisser metrique article ou Cliquez sur le bouton Ajouter]]></li><li group="locale_en_US_225" name="L_F_SQL_IS_NOT"><![CDATA[SQL Is Not Operateur (EST PAS)]]></li><li group="locale_en_US_225" name="L_F_BETWEEN_NOT"><![CDATA[Pas entre les valeurs (PAS ENTRE)]]></li><li group="locale_en_US_225" name="L_F_LIKE_NOT"><![CDATA[Non Inclure mot-cle (NOT LIKE)]]></li><li group="locale_en_US_225" name="L_F_IN_NOT"><![CDATA[Pas dans la liste (PAS EN)]]></li><li group="locale_en_US_225" name="L_F_GE"><![CDATA[Superieur ou egal (> =)]]></li><li group="locale_en_US_225" name="L_F_GT"><![CDATA[Grand ensuite (>)]]></li><li group="locale_en_US_225" name="L_F_LT_NOT"><![CDATA[Non Moins (> =)]]></li><li group="locale_en_US_225" name="L_F_LE_NOT"><![CDATA[Non Inferieur ou egal (>)]]></li><li group="locale_en_US_225" name="L_P_CLUSTER"><![CDATA[Dimension Cluster]]></li><li group="locale_en_US_225" name="L_F_LT"><![CDATA[Moins de (<)]]></li><li group="locale_en_US_225" name="L_F_LE"><![CDATA[Inferieur ou egal (<=)]]></li><li group="locale_en_US_225" name="L_F_LIKE"><![CDATA[Inclure les mots cles (comme)]]></li><li group="locale_en_US_225" name="L_F_GE_NOT"><![CDATA[Non Superieur ou egal (<)]]></li><li group="locale_en_US_225" name="L_F_EQ_NOT"><![CDATA[Not Equal (<>)]]></li><li group="locale_en_US_225" name="L_F_SQL_IS"><![CDATA[SQL est operateur (EST)]]></li><li group="locale_en_US_225" name="L_SEARCH_KWD"><![CDATA[Recherche]]></li><li group="locale_en_US_225" name="D_FORMULAMEASURE"><![CDATA[Formule]]></li><li group="locale_en_US_225" name="L_SERIES"><![CDATA[Option de serie]]></li><li group="locale_en_US_225" name="T_CHART_SERIES"><![CDATA[Tableau Serie]]></li><li group="locale_en_US_225" name="L_F_IN"><![CDATA[Dans la liste (EN)]]></li><li group="locale_en_US_225" name="L_F_EQ"><![CDATA[Egal (=)]]></li><li group="locale_en_US_224" name="L_OP_NOT"><![CDATA[Non Operation]]></li><li group="locale_en_US_224" name="T_RPT_PIVOT"><![CDATA[Rapport Pivot]]></li><li group="locale_en_US_224" name="L_B_USR"><![CDATA[Utilisateurs bloques]]></li><li group="locale_en_US_224" name="L_A_USR"><![CDATA[Utilisateurs actifs]]></li><li group="locale_en_US_224" name="B_APPLY"><![CDATA[Appliquer]]></li><li group="locale_en_US_224" name="M_NOT_EDITABLE"><![CDATA[Non autorise a modifier cet article!]]></li><li group="locale_en_US_224" name="L_B_CUBE"><![CDATA[Traitement de Cube]]></li><li group="locale_en_US_223" name="M_NA"><![CDATA[Non autorises operations.]]></li><li group="locale_en_US_223" name="L_M_SUBJ_REC"><![CDATA[Elements utilises recemment]]></li><li group="locale_en_US_223" name="L_M_SUBJ"><![CDATA[Analyse Objet:]]></li><li group="locale_en_US_223" name="L_M_CUBE_SEL"><![CDATA[Selectionnez l'analyse du sujet ...]]></li><li group="locale_en_US_223" name="L_T_CUBE_SEL"><![CDATA[Selectionnez Data Wizard]]></li><li group="locale_en_US_223" name="L_FETCH_ALL"><![CDATA[Fetch Toutes les donnees]]></li><li group="locale_en_US_223" name="L_C_SCH"><![CDATA[Charge avec les resultats de la planification. Voudriez-vous interroger au serveur?]]></li><li group="locale_en_US_223" name="L_LINE_NUM"><![CDATA[Numero de ligne]]></li><li group="locale_en_US_222" name="B_NO"><![CDATA[Non]]></li><li group="locale_en_US_222" name="B_YES"><![CDATA[Oui]]></li><li group="locale_en_US_222" name="L_T_LOUT"><![CDATA[Souhaitez-vous deconnecter du systeme?]]></li><li group="locale_en_US_222" name="B_CANCEL"><![CDATA[Annuler]]></li><li group="locale_en_US_222" name="B_OK"><![CDATA[D'accord]]></li><li group="locale_en_US_221" name="L_C_TOTAL"><![CDATA[Le total @]]></li><li group="locale_en_US_221" name="L_BUILD_CUBE"><![CDATA[Construire Cube]]></li><li group="locale_en_US_221" name="L_BB_STEP_3"><![CDATA[Assurez-mesures et Temps Metrics]]></li><li group="locale_en_US_221" name="L_BB_STEP_2"><![CDATA[Creer des structures de dossiers]]></li><li group="locale_en_US_221" name="B_B_CUBE"><![CDATA[Cliquez sur Continuer pour lancer le processus automatique de creation de cube.]]></li><li group="locale_en_US_221" name="L_BB_STEP_1"><![CDATA[Preparation de donnees]]></li><li group="locale_en_US_221" name="L_C_DCOUNT"><![CDATA[@ Comtes]]></li><li group="locale_en_US_221" name="L_C_DATE"><![CDATA[Detail de @]]></li><li group="locale_en_US_221" name="L_BUILD"><![CDATA[Suggeree Construire Point]]></li><li group="locale_en_US_221" name="M_DETAIL"><![CDATA[Details]]></li><li group="locale_en_US_221" name="L_TB_PRT_T"><![CDATA[Export cible (s)]]></li><li group="locale_en_US_221" name="L_TB_PRT"><![CDATA[Boutons d'exportation]]></li><li group="locale_en_US_221" name="L_TB_PRT_GRD"><![CDATA[Exporter Grille]]></li><li group="locale_en_US_221" name="L_TB_VCH"><![CDATA[Change de vue]]></li><li group="locale_en_US_221" name="L_OPT_TBAR"><![CDATA[La barre de titre d'options]]></li><li group="locale_en_US_221" name="L_BUILD_MODEL"><![CDATA[Model Wizard]]></li><li group="locale_en_US_220" name="L_DET_VIEW"><![CDATA[vue detaillee]]></li><li group="locale_en_US_220" name="L_DATE_FORMAT_TGT"><![CDATA[Affichage de la date Format]]></li><li group="locale_en_US_220" name="L_DATE_FORMAT_SRC"><![CDATA[Source Date Format]]></li><li group="locale_en_US_220" name="L_P_RPT_C"><![CDATA[Rapport sur les options]]></li><li group="locale_en_US_220" name="L_P_RELOAD"><![CDATA[Cliquez sur Actualiser pour charger.]]></li><li group="locale_en_US_220" name="E_SWA_CFM"><![CDATA[S'il vous plait selectionnez le nom de l'application pour passer.]]></li><li group="locale_en_US_220" name="L_SWA_CFM"><![CDATA[Voulez-vous continuer a deconnecter et vous connecter a un autre projet?]]></li><li group="locale_en_US_220" name="L_SW_APP"><![CDATA[Changer d'application]]></li><li group="locale_en_US_219" name="L_HD_MAPR"><![CDATA[Carte Reduire]]></li><li group="locale_en_US_219" name="L_HD_BFLOW"><![CDATA[Hadoop BizFlow]]></li><li group="locale_en_US_219" name="L_BIGDATA"><![CDATA[Big Data]]></li><li group="locale_en_US_219" name="L_HADOOP"><![CDATA[Gestion Hadoop]]></li><li group="locale_en_US_218" name="L_C_D_NAMES"><![CDATA[Dimanche Lundi Mardi Mercredi Jeudi Vendredi Samedi]]></li><li group="locale_en_US_218" name="B_SAVE"><![CDATA[Conserver]]></li><li group="locale_en_US_218" name="L_RESOURCE"><![CDATA[Ressources]]></li><li group="locale_en_US_218" name="L_CLASS_MOD"><![CDATA[Module de classe]]></li><li group="locale_en_US_218" name="L_SEL_MODE"><![CDATA[Selectionnez le mode]]></li><li group="locale_en_US_218" name="L_CLEAR_FLT"><![CDATA[Clear Filter]]></li><li group="locale_en_US_218" name="L_C_YR_SFX"><![CDATA[An]]></li><li group="locale_en_US_218" name="L_C_W_H"><![CDATA[Semaine]]></li><li group="locale_en_US_218" name="L_FILENAME"><![CDATA[Nom de fichier]]></li><li group="locale_en_US_218" name="L_C_D_NAMES_S"><![CDATA[Sun # Lun Mar # # # Mer Jeu Ven # # sam]]></li><li group="locale_en_US_218" name="L_MENU"><![CDATA[le menu]]></li><li group="locale_en_US_218" name="L_C_M_NAMES_S"><![CDATA[JAN # # fevrier MAR # # avril MAI # # juin juillet aout # # # septembre octobre novembre # # decembre]]></li><li group="locale_en_US_218" name="L_C_M_NAMES"><![CDATA[Janvier Fevrier # # # Mars Avril Mai # # # Juin Juillet Aout # # # Septembre Octobre Novembre # # Decembre]]></li><li group="locale_en_US_218" name="L_C_CUR"><![CDATA[Actuel,]]></li><li group="locale_en_US_218" name="L_C_NEXT"><![CDATA[la prochaine]]></li><li group="locale_en_US_218" name="L_C_PREV"><![CDATA[Precedent]]></li><li group="locale_en_US_218" name="L_C_CLOSE"><![CDATA[Pres]]></li><li group="locale_en_US_218" name="L_RESOURCES"><![CDATA[Ressources]]></li><li group="locale_en_US_218" name="L_CONTROLLER"><![CDATA[Controle]]></li><li group="locale_en_US_218" name="L_C_D_NAMES_M"><![CDATA[SU MO # # # TU NOUS # TH FR # # SA]]></li><li group="locale_en_US_217" name="L_B_LAYOUT"><![CDATA[Disposition des frontieres]]></li><li group="locale_en_US_217" name="L_B_ADC"><![CDATA[Telecharger le fichier]]></li><li group="locale_en_US_217" name="L_NEW_RPT_VIEWER"><![CDATA[New Report Viewer]]></li><li group="locale_en_US_217" name="L_NEW_PANEL"><![CDATA[Nouveau panneau]]></li><li group="locale_en_US_217" name="B_ID"><![CDATA[ID]]></li><li group="locale_en_US_217" name="L_R_FIXSIZE"><![CDATA[Taille fixe]]></li><li group="locale_en_US_217" name="B_HEIGHT"><![CDATA[Hauteur]]></li><li group="locale_en_US_217" name="B_WIDTH"><![CDATA[Largeur]]></li><li group="locale_en_US_217" name="L_RPT_V_OPT"><![CDATA[Option Report Viewer]]></li><li group="locale_en_US_217" name="L_L_TAB"><![CDATA[Chargez dernier onglet seulement]]></li><li group="locale_en_US_217" name="L_C_DEL_ITEM"><![CDATA[Voulez-vous de retirer l'article?]]></li><li group="locale_en_US_217" name="L_SQL_PRE"><![CDATA[Traitement Pre]]></li><li group="locale_en_US_216" name="L_REN_SCH"><![CDATA[Changer de nom]]></li><li group="locale_en_US_216" name="E_SC_LD"><![CDATA[Erreur lors du chargement DynamicScript]]></li><li group="locale_en_US_216" name="L_UNIT_TEXT"><![CDATA[Unite texte]]></li><li group="locale_en_US_216" name="L_SHOW_VALUE"><![CDATA[Afficher les valeurs]]></li><li group="locale_en_US_216" name="E_D_EVNT"><![CDATA[Erreur lors du traitement EvNet @.]]></li><li group="locale_en_US_216" name="M_S_S2"><![CDATA[Aucun resultat trouve pour les tableaux enregistres.]]></li><li group="locale_en_US_216" name="M_S_S1"><![CDATA[Aucun resultat pour instance de base de donnees selectionnee.]]></li><li group="locale_en_US_216" name="L_C_FMT_VAL"><![CDATA[Utiliser formate Valeur]]></li><li group="locale_en_US_216" name="L_EXPORT_CSV"><![CDATA[CSV]]></li><li group="locale_en_US_216" name="L_EVENT_WIZARD"><![CDATA[Assistant Action]]></li><li group="locale_en_US_215" name="L_EXP_MET_DESC"><![CDATA[Cochez les articles de menu a utiliser dans le present rapport.]]></li><li group="locale_en_US_215" name="L_EXP_JASP"><![CDATA[Jaspe]]></li><li group="locale_en_US_215" name="L_EXPORT_JASPER"><![CDATA[JasperReport]]></li><li group="locale_en_US_215" name="L_EXP_MET"><![CDATA[Controle de Menu]]></li><li group="locale_en_US_215" name="L_EXPORT_HTML"><![CDATA[HTML Voir]]></li><li group="locale_en_US_214" name="W_SYNC_USER"><![CDATA[Voulez-vous proceder a la synchronisation de l'utilisateur dans le serveur?]]></li><li group="locale_en_US_214" name="W_SYNC_GRP"><![CDATA[Voulez-vous proceder a la synchronisation de groupe dans le serveur?]]></li><li group="locale_en_US_214" name="T_SYNC_USER"><![CDATA[Utilisateur Sync]]></li><li group="locale_en_US_214" name="W_SYNC_SAVE"><![CDATA[Voulez-vous sauver le parametre de synchronisation de l'utilisateur dans le serveur?]]></li><li group="locale_en_US_213" name="L_TABLE_DROP"><![CDATA[Pour vous inscrire Field glisser pour la region Moyen.]]></li><li group="locale_en_US_212" name="M_SUCCESS"><![CDATA[Succes!]]></li><li group="locale_en_US_212" name="L_P_RPT_RT"><![CDATA[Pivot Composite]]></li><li group="locale_en_US_212" name="L_P_RPT"><![CDATA[Pivot Composite]]></li><li group="locale_en_US_212" name="L_V_RPT"><![CDATA[Mode Pivot Composite]]></li><li group="locale_en_US_212" name="L_V_PIVOT"><![CDATA[Mode Pivot]]></li><li group="locale_en_US_212" name="L_P_PIVOT_UNIT"><![CDATA[Unite Pivot]]></li><li group="locale_en_US_212" name="M_INFO"><![CDATA[Info!]]></li><li group="locale_en_US_212" name="M_WARNING"><![CDATA[Attention!]]></li><li group="locale_en_US_212" name="M_UNKNOWN"><![CDATA[Erreur inconnue!]]></li><li group="locale_en_US_212" name="E_NO_MATCH_FLD"><![CDATA[Pas trouve correspondant a l'article de la liste.]]></li><li group="locale_en_US_212" name="L_MOVE"><![CDATA[Deplacer]]></li><li group="locale_en_US_211" name="L_S_GRST"><![CDATA[Resultats du Groupe]]></li><li group="locale_en_US_211" name="L_MONITORING"><![CDATA[suivi]]></li><li group="locale_en_US_211" name="L_MGR_DASHBOARD"><![CDATA[Mgr Dashaboard]]></li><li group="locale_en_US_211" name="L_VARIABLES"><![CDATA[Variables]]></li><li group="locale_en_US_211" name="B_ZOOM"><![CDATA[Zoom]]></li><li group="locale_en_US_211" name="L_MAP_TYPE"><![CDATA[Carte Type]]></li><li group="locale_en_US_211" name="B_TITLE"><![CDATA[Titre]]></li><li group="locale_en_US_211" name="L_MAP_OPT"><![CDATA[Options Carte]]></li><li group="locale_en_US_211" name="L_DATE_FORMAT"><![CDATA[Format de date]]></li><li group="locale_en_US_211" name="L_TC_DU"><![CDATA[Duree (mili seconde)]]></li><li group="locale_en_US_211" name="B_OVERFLOW"><![CDATA[Debordement]]></li><li group="locale_en_US_211" name="L_REG_TABLE"><![CDATA[Tableau Enregistrer]]></li><li group="locale_en_US_211" name="L_RANK_BOTTOM"><![CDATA[Bottom Rang]]></li><li group="locale_en_US_211" name="L_TC_TA"><![CDATA[L'axe du temps]]></li><li group="locale_en_US_211" name="L_BB_MS"><![CDATA[Taille maximale de la bulle]]></li><li group="locale_en_US_211" name="B_HIDE"><![CDATA[Cache]]></li><li group="locale_en_US_211" name="L_BB_CA"><![CDATA[Bubble Couleur Axe]]></li><li group="locale_en_US_211" name="L_BB_SA"><![CDATA[Bubble Taille Axis]]></li><li group="locale_en_US_211" name="L_ENABLE_PIVOT"><![CDATA[Activer Pivot]]></li><li group="locale_en_US_211" name="L_DB_INSTANCE"><![CDATA[Instance de base]]></li><li group="locale_en_US_211" name="L_OVF_DESC"><![CDATA[Verifiez debordement pour tirage defiler grille]]></li><li group="locale_en_US_211" name="L_SHEET_OPTIONS"><![CDATA[Options de la feuille]]></li><li group="locale_en_US_211" name="L_ANALYSIS"><![CDATA[Une analyse]]></li><li group="locale_en_US_211" name="L_PAGE_OPTIONS"><![CDATA[Options de page]]></li><li group="locale_en_US_211" name="L_BB_YA"><![CDATA[Donnees de ligne a l'axe Y]]></li><li group="locale_en_US_211" name="L_FEATURE_CTRL"><![CDATA[Les controles de fonctionnalites]]></li><li group="locale_en_US_211" name="L_ALIGN_VERTICAL"><![CDATA[Alignement vertical]]></li><li group="locale_en_US_211" name="L_LOCALE_MANAGER"><![CDATA[Gestionnaire Locale]]></li><li group="locale_en_US_211" name="B_NUMERIC"><![CDATA[Numerique]]></li><li group="locale_en_US_211" name="B_VALUES"><![CDATA[Valeurs]]></li><li group="locale_en_US_211" name="L_CVAL_DESC"><![CDATA[Type de texte avec separateur point-virgule]]></li><li group="locale_en_US_211" name="B_METHOD"><![CDATA[la methode]]></li><li group="locale_en_US_211" name="B_TEXT"><![CDATA[Envoyer des textos]]></li><li group="locale_en_US_211" name="L_RANK_TOP"><![CDATA[Top Rank]]></li><li group="locale_en_US_211" name="L_HELP_DOC"><![CDATA[Aide Documentation]]></li><li group="locale_en_US_211" name="L_BB_SL"><![CDATA[Afficher la legende rowData]]></li><li group="locale_en_US_211" name="L_SORT_SEL"><![CDATA[Methodes de tri]]></li><li group="locale_en_US_211" name="L_LOOK_AND_FEEL"><![CDATA[Regarde et ressent]]></li><li group="locale_en_US_211" name="L_YAXIS_TITLE"><![CDATA[AxeY Titre]]></li><li group="locale_en_US_211" name="B_CODE"><![CDATA[Code]]></li><li group="locale_en_US_211" name="L_USER_MANAGEMENT"><![CDATA[Gestion des utilisateurs]]></li><li group="locale_en_US_211" name="L_SYSTEM"><![CDATA[Systeme]]></li><li group="locale_en_US_211" name="T_VALUE_SELECT"><![CDATA[Assistant de selection de valeur]]></li><li group="locale_en_US_211" name="L_DF_OS"><![CDATA[Le style de commande]]></li><li group="locale_en_US_211" name="L_SORT_ORD"><![CDATA[Ordres de tri]]></li><li group="locale_en_US_211" name="L_DF_MF"><![CDATA[Mois Format]]></li><li group="locale_en_US_211" name="L_LOGOUT"><![CDATA[Se deconnecter]]></li><li group="locale_en_US_211" name="L_BB_OPT"><![CDATA[Options de BubbleMap]]></li><li group="locale_en_US_211" name="L_CH_PASSWD"><![CDATA[Changer le mot de passe]]></li><li group="locale_en_US_211" name="L_PREFERENCES"><![CDATA[Preferences]]></li><li group="locale_en_US_211" name="B_BACK"><![CDATA[Arriere]]></li><li group="locale_en_US_211" name="B_DSC"><![CDATA[Descendant]]></li><li group="locale_en_US_211" name="L_F_VALUE_TO"><![CDATA[Estimer]]></li><li group="locale_en_US_211" name="L_CLR_SET"><![CDATA[Definir la couleur]]></li><li group="locale_en_US_211" name="L_DF_YF"><![CDATA[Annee Format]]></li><li group="locale_en_US_211" name="L_F_VALUE_LNG"><![CDATA[Valeurs]]></li><li group="locale_en_US_211" name="L_SORT_SRC"><![CDATA[Articles pour trier]]></li><li group="locale_en_US_211" name="B_ASC"><![CDATA[Ascendant]]></li><li group="locale_en_US_211" name="L_HELP_GUIDES"><![CDATA[Aide et Guides]]></li><li group="locale_en_US_211" name="L_F_VALUE"><![CDATA[Valeur]]></li><li group="locale_en_US_211" name="L_PROMPT_TYPE"><![CDATA[Prompt type]]></li><li group="locale_en_US_211" name="L_RNK_LST"><![CDATA[Afficher tout dernier rang]]></li><li group="locale_en_US_211" name="L_RNK_PAR"><![CDATA[Par Partition]]></li><li group="locale_en_US_211" name="L_VAL_DELIM"><![CDATA[Valeur Delimiteur]]></li><li group="locale_en_US_211" name="L_PLOT_STYLES"><![CDATA[Styles de trace]]></li><li group="locale_en_US_211" name="L_MANAGEMENT"><![CDATA[Gestion]]></li><li group="locale_en_US_211" name="L_HIGH_PREC"><![CDATA[Numero de haute precision]]></li><li group="locale_en_US_211" name="L_NUM_PREC"><![CDATA[Nombre de precision]]></li><li group="locale_en_US_211" name="L_OTHER_OPTION"><![CDATA[Autre options]]></li><li group="locale_en_US_211" name="L_E_LIST"><![CDATA[Selectionnez des valeurs]]></li><li group="locale_en_US_211" name="L_E_VALUE"><![CDATA[Type Valeurs]]></li><li group="locale_en_US_211" name="L_RNK_CNT"><![CDATA[Nombre de Rang]]></li><li group="locale_en_US_211" name="L_COL_TREE"><![CDATA[Assurez-Colonne Arbre tete]]></li><li group="locale_en_US_211" name="L_EDITOR_TYPE"><![CDATA[Type d'editeur]]></li><li group="locale_en_US_211" name="L_ENABLE_TREE_VIEW"><![CDATA[Activer Tree View]]></li><li group="locale_en_US_211" name="L_TREE_VIEW"><![CDATA[Arborescence]]></li><li group="locale_en_US_211" name="L_SYS_RES"><![CDATA[Ressources systeme]]></li><li group="locale_en_US_211" name="L_SERIES_TYPE"><![CDATA[Type de serie]]></li><li group="locale_en_US_211" name="L_PAGE_STYLE"><![CDATA[Style de page]]></li><li group="locale_en_US_211" name="L_ROW_P_PAGE"><![CDATA[Lignes par page]]></li><li group="locale_en_US_211" name="L_SYS_LOG"><![CDATA[Journal systeme]]></li><li group="locale_en_US_211" name="L_SERIES_LAYOUT"><![CDATA[Mise en page de la serie]]></li><li group="locale_en_US_211" name="L_USE_PAGING"><![CDATA[Utiliser la pagination]]></li><li group="locale_en_US_211" name="L_PAGING"><![CDATA[Pagination]]></li><li group="locale_en_US_211" name="L_M_NAME"><![CDATA[Nom de la mesure]]></li><li group="locale_en_US_211" name="L_RNK_VAL"><![CDATA[Classement de la Valeur]]></li><li group="locale_en_US_211" name="L_MAP_AXIS"><![CDATA[Carte Axis]]></li><li group="locale_en_US_211" name="L_M_FORMAT"><![CDATA[Mesure Format]]></li><li group="locale_en_US_211" name="L_RANGE_FIELD"><![CDATA[Range Champ]]></li><li group="locale_en_US_211" name="L_BASE_METRIC"><![CDATA[Base de Metric]]></li><li group="locale_en_US_211" name="B_CLEAR"><![CDATA[Clair]]></li><li group="locale_en_US_211" name="L_F_SORT"><![CDATA[Le champ de tri]]></li><li group="locale_en_US_211" name="L_F_DISP"><![CDATA[Champ d'affichage]]></li><li group="locale_en_US_211" name="L_DATE_TYPE"><![CDATA[Date Type de terrain]]></li><li group="locale_en_US_211" name="L_REM_BLK"><![CDATA[Retirer les valeurs a blanc]]></li><li group="locale_en_US_211" name="L_BASE_STYLE"><![CDATA[Style de base]]></li><li group="locale_en_US_211" name="L_FUNC"><![CDATA[Fonction]]></li><li group="locale_en_US_211" name="L_COL_VIS"><![CDATA[Colonne Visible]]></li><li group="locale_en_US_211" name="L_SEP_COL"><![CDATA[Colonne distincte]]></li><li group="locale_en_US_211" name="L_C_DIR"><![CDATA[Calculer Direction]]></li><li group="locale_en_US_211" name="L_CUSTOM_FIX"><![CDATA[Fix personnalisee]]></li><li group="locale_en_US_211" name="L_FORMAT"><![CDATA[Format]]></li><li group="locale_en_US_211" name="L_FIX_COLUMN"><![CDATA[Fix Colonne]]></li><li group="locale_en_US_211" name="L_S_TROW"><![CDATA[Voir sur la rangee du haut]]></li><li group="locale_en_US_211" name="L_DISTINCT"><![CDATA[Retour distinctes toutes les lignes]]></li><li group="locale_en_US_211" name="L_MEASURE_ON"><![CDATA[Sur Mesure]]></li><li group="locale_en_US_211" name="L_M_POSITION"><![CDATA[Mesurer la position]]></li><li group="locale_en_US_211" name="L_USE_MFMT"><![CDATA[Utiliser Mesure Format]]></li><li group="locale_en_US_211" name="L_TIME_FMT_DSC"><![CDATA[* Applique si le format de date article]]></li><li group="locale_en_US_211" name="L_TIME_FMT"><![CDATA[Format de l'heure]]></li><li group="locale_en_US_211" name="L_DISP_TITLE"><![CDATA[Affichage Titre]]></li><li group="locale_en_US_211" name="L_AGGR"><![CDATA[Agregation]]></li><li group="locale_en_US_211" name="L_SORT_TP"><![CDATA[Type de tri]]></li><li group="locale_en_US_211" name="B_STRING"><![CDATA[Chaine]]></li><li group="locale_en_US_211" name="L_BTN_ROW_ON"><![CDATA[Bouton au n ° Row]]></li><li group="locale_en_US_211" name="L_ROW_SIZE"><![CDATA[Taille de Row]]></li><li group="locale_en_US_211" name="L_COL_SIZE"><![CDATA[Colonne Taille]]></li><li group="locale_en_US_211" name="L_META_IMPORT"><![CDATA[Importer Meta File]]></li><li group="locale_en_US_211" name="L_RUN_BUTTON"><![CDATA[Bouton Executer]]></li><li group="locale_en_US_211" name="L_OBJECT_TYPE"><![CDATA[Type d'objet]]></li><li group="locale_en_US_211" name="L_EMPTY_DATA"><![CDATA[Vide dans cette liste]]></li><li group="locale_en_US_211" name="L_TABLES"><![CDATA[Tableau Source]]></li><li group="locale_en_US_211" name="L_FOLDER_ITEMS"><![CDATA[Dossier Articles]]></li><li group="locale_en_US_211" name="L_CREATE_ITEM"><![CDATA[Creer un element]]></li><li group="locale_en_US_211" name="L_ADD_DB_INST"><![CDATA[Ajouter Instance de base]]></li><li group="locale_en_US_211" name="L_PANEL_H"><![CDATA[Hauteur du panneau]]></li><li group="locale_en_US_211" name="L_PANEL_W"><![CDATA[Largeur panneau]]></li><li group="locale_en_US_211" name="L_ADD_TENANT"><![CDATA[Ajouter locataire]]></li><li group="locale_en_US_211" name="L_VIEW_MODE_LBL"><![CDATA[Requete de donnees spectateur]]></li><li group="locale_en_US_211" name="T_M_TENANT"><![CDATA[Multi locataires]]></li><li group="locale_en_US_211" name="L_ADD_DUTY"><![CDATA[Ajouter Duty]]></li><li group="locale_en_US_211" name="L_VIEW_MODE"><![CDATA[Mode d'affichage]]></li><li group="locale_en_US_211" name="L_P_MEASURE"><![CDATA[Les mesures]]></li><li group="locale_en_US_211" name="T_DUTY_LIST"><![CDATA[Liste Duty]]></li><li group="locale_en_US_211" name="T_USER_GROUP"><![CDATA[Groupes d'utilisateurs]]></li><li group="locale_en_US_211" name="L_PRIVILEGE"><![CDATA[Privilege]]></li><li group="locale_en_US_211" name="L_ADD_GROUP"><![CDATA[Ajouter un groupe]]></li><li group="locale_en_US_211" name="L_ADD_USER"><![CDATA[Ajouter un utilisateur]]></li><li group="locale_en_US_211" name="L_P_COL"><![CDATA[Colonne Dimensios]]></li><li group="locale_en_US_211" name="L_MARKER"><![CDATA[Marqueur]]></li><li group="locale_en_US_211" name="L_P_ROW"><![CDATA[Row Dimensions]]></li><li group="locale_en_US_211" name="L_SAVE_C_MSG"><![CDATA[Vous fermez un onglet des modifications non enregistrees. Aimeriez-vous pour enregistrer vos modifications?]]></li><li group="locale_en_US_211" name="L_SAVE_CHANGES"><![CDATA[Sauvegarder les modifications?]]></li><li group="locale_en_US_211" name="L_MGR_UD"><![CDATA[Gestion de service de l'utilisateur]]></li><li group="locale_en_US_211" name="L_UD_DESC"><![CDATA[Selectionnez le devoir de l'utilisateur de la liste.]]></li><li group="locale_en_US_211" name="L_LAST_UPD"><![CDATA[La derniere fois mise a jour:]]></li><li group="locale_en_US_211" name="L_DF_DF"><![CDATA[Jour Format]]></li><li group="locale_en_US_211" name="L_DF_WF"><![CDATA[Jour de la semaine Format]]></li><li group="locale_en_US_211" name="L_USER_DUTY"><![CDATA[Obligation de l'utilisateur]]></li><li group="locale_en_US_211" name="L_EMAIL"><![CDATA[Email]]></li><li group="locale_en_US_211" name="L_DEPRIVATE"><![CDATA[Verrouillage utilisateur de Connexion]]></li><li group="locale_en_US_211" name="L_DF_APM"><![CDATA[MATIN APRES-MIDI]]></li><li group="locale_en_US_211" name="L_DF_WD"><![CDATA[Jour de la semaine]]></li><li group="locale_en_US_211" name="L_ACTIVATE"><![CDATA[Activer]]></li><li group="locale_en_US_211" name="L_DF_WD_O"><![CDATA[Weekday Ordre]]></li><li group="locale_en_US_211" name="L_USERNAME"><![CDATA[Nom d'utilisateur]]></li><li group="locale_en_US_211" name="L_USERID"><![CDATA[ID de l'utilisateur]]></li><li group="locale_en_US_211" name="L_TIMEZONE"><![CDATA[Fuseau horaire]]></li><li group="locale_en_US_211" name="L_GROUP_NAME"><![CDATA[Nom de groupe]]></li><li group="locale_en_US_211" name="T_REG_USER"><![CDATA[Inscription utilisateur]]></li><li group="locale_en_US_211" name="L_SHOW_TZ"><![CDATA[Afficher Fuseau horaire]]></li><li group="locale_en_US_211" name="L_SHOW_FIRST"><![CDATA[Montrer d'abord]]></li><li group="locale_en_US_211" name="L_OPTIONS"><![CDATA[Options]]></li><li group="locale_en_US_211" name="L_APPL_TMPL"><![CDATA[Modele de demande]]></li><li group="locale_en_US_211" name="L_APPL"><![CDATA[Application]]></li><li group="locale_en_US_211" name="L_TZ_OFFSET"><![CDATA[Decalage horaire]]></li><li group="locale_en_US_211" name="L_DF_TS"><![CDATA[Temps separee]]></li><li group="locale_en_US_211" name="L_DF_DS"><![CDATA[Date de separee]]></li><li group="locale_en_US_210" name="L_SCHEMA_NAME"><![CDATA[Nom du schema]]></li><li group="locale_en_US_210" name="L_JDBC_DRV"><![CDATA[JDBC Driver]]></li><li group="locale_en_US_210" name="L_LATITUDE"><![CDATA[Latitude]]></li><li group="locale_en_US_210" name="L_GEO_FIELD"><![CDATA[Emplacement geographique]]></li><li group="locale_en_US_210" name="T_CHART_PLOTBAND"><![CDATA[Graphique Terrain Band]]></li><li group="locale_en_US_210" name="L_BAND_BORDER"><![CDATA[Frontiere]]></li><li group="locale_en_US_210" name="L_BAND_COLOR"><![CDATA[Couleur]]></li><li group="locale_en_US_210" name="L_BAND_VALUE_2"><![CDATA[Valeur a]]></li><li group="locale_en_US_210" name="L_BAND_VALUE_1"><![CDATA[Valeur]]></li><li group="locale_en_US_210" name="L_BAND_TYPE"><![CDATA[Type de bande]]></li><li group="locale_en_US_210" name="L_CSTEP_6"><![CDATA[Bandes]]></li><li group="locale_en_US_210" name="L_ADD_NEW"><![CDATA[Ajouter un nouveau]]></li><li group="locale_en_US_210" name="B_STATUS"><![CDATA[statut]]></li><li group="locale_en_US_210" name="L_ROW_LIMIT_COUNT"><![CDATA[Count Limit]]></li><li group="locale_en_US_210" name="L_OUTPUT_CHARSET"><![CDATA[CharSet de sortie]]></li><li group="locale_en_US_210" name="L_DB_CHARSET"><![CDATA[DB CharSet]]></li><li group="locale_en_US_210" name="L_DB_PWD"><![CDATA[Mot de passe]]></li><li group="locale_en_US_210" name="L_DB_UNAME"><![CDATA[Nom d'utilisateur]]></li><li group="locale_en_US_210" name="L_LONGITUDE"><![CDATA[Longitude]]></li><li group="locale_en_US_210" name="L_JDBC_URL"><![CDATA[URL JDBC]]></li><li group="locale_en_US_210" name="L_APPLY_TMPL"><![CDATA[Appliquer le modele]]></li><li group="locale_en_US_210" name="L_DB_TYPE"><![CDATA[Type de base de donnees]]></li><li group="locale_en_US_210" name="L_DB_NAME"><![CDATA[Nom de base de donnee]]></li><li group="locale_en_US_210" name="T_DB_CON"><![CDATA[Instances de base]]></li><li group="locale_en_US_210" name="L_CODEMAPPING"><![CDATA[CodeMapping]]></li><li group="locale_en_US_210" name="L_RENAME"><![CDATA[Rebaptiser]]></li><li group="locale_en_US_210" name="L_ADV_OPTION"><![CDATA[Options avancees]]></li><li group="locale_en_US_210" name="L_SCHEMA"><![CDATA[Schema]]></li><li group="locale_en_US_210" name="L_NEW_TABPANEL"><![CDATA[Nouveau TabPanel]]></li><li group="locale_en_US_210" name="L_NEW_TEXTAREA"><![CDATA[Nouveau TextArea]]></li><li group="locale_en_US_210" name="L_NEW_FILTER"><![CDATA[Nouveau filtre]]></li><li group="locale_en_US_210" name="L_NEW_SHEET"><![CDATA[Nouvelle feuille]]></li><li group="locale_en_US_210" name="B_ENABLE"><![CDATA[Activer]]></li><li group="locale_en_US_210" name="B_INSIDE"><![CDATA[A l'interieur]]></li><li group="locale_en_US_210" name="L_LABEL_ALIGN"><![CDATA[Etiquette Aligner]]></li><li group="locale_en_US_210" name="L_DATA_LABEL"><![CDATA[Etiquettes de donnees]]></li><li group="locale_en_US_209" name="L_F_NOTIN"><![CDATA[N'incluant pas]]></li><li group="locale_en_US_209" name="L_R_ANAL_CUBE_LBL"><![CDATA[Fiche Cube]]></li><li group="locale_en_US_209" name="B_NO_DATA"><![CDATA[Aucune donnee]]></li><li group="locale_en_US_209" name="D_SCHEMA"><![CDATA[Schema]]></li><li group="locale_en_US_208" name="D_AUTH"><![CDATA[Devoir]]></li><li group="locale_en_US_208" name="T_EXP_MC_Q"><![CDATA[Souhaitez-vous continuer a exporter le contenu de deposer?]]></li><li group="locale_en_US_208" name="L_S_LK"><![CDATA[Code de cartographie de gestion]]></li><li group="locale_en_US_208" name="D_CODEMAP"><![CDATA[Cartographie de code]]></li><li group="locale_en_US_208" name="T_M_MEASURE"><![CDATA[Assurez-mesures]]></li><li group="locale_en_US_208" name="L_MENU_DB_MODEL"><![CDATA[Base de donnees de modele]]></li><li group="locale_en_US_208" name="D_CLASSMODULE"><![CDATA[ClassModule]]></li><li group="locale_en_US_208" name="D_TENANT"><![CDATA[Locataire]]></li><li group="locale_en_US_208" name="L_EXPORT_PRINT"><![CDATA[HTML Imprimer]]></li><li group="locale_en_US_208" name="I_MGR_DBD"><![CDATA[Dashboard Builder Logic]]></li><li group="locale_en_US_208" name="T_EXP_MC"><![CDATA[Contenu de l'exportation]]></li><li group="locale_en_US_205" name="L_WORKSPACE"><![CDATA[Nouvel espace de travail]]></li><li group="locale_en_US_204" name="D_NOSQL"><![CDATA[Base de donnees NoSQL]]></li><li group="locale_en_US_204" name="D_MCUBE"><![CDATA[MultiDimension Cube]]></li><li group="locale_en_US_204" name="L_MAP_ITEM"><![CDATA[Plan d'element de rapport]]></li><li group="locale_en_US_204" name="B_REQ"><![CDATA[Champ requis]]></li><li group="locale_en_US_204" name="M_ERR_C_REP_PROC"><![CDATA[Erreur lors du traitement de rapport personnalise Handler]]></li><li group="locale_en_US_204" name="T_Filter"><![CDATA[Filtrer les donnees]]></li><li group="locale_en_US_204" name="L_P_open_dlg"><![CDATA[Ouvrir la boite de dialogue]]></li><li group="locale_en_US_204" name="L_P_inv_svc"><![CDATA[Appelez service]]></li><li group="locale_en_US_204" name="L_WAIT_1"><![CDATA[S'il vous plait patienter pendant que le traitement de la demande]]></li><li group="locale_en_US_204" name="L_DBD_MAP"><![CDATA[Cartographie de Dashboard]]></li><li group="locale_en_US_204" name="L_P_onlinereport"><![CDATA[Executer le rapport]]></li><li group="locale_en_US_204" name="L_P_valuelist"><![CDATA[Remplissez Valeurs]]></li><li group="locale_en_US_204" name="B_DISP_NAME"><![CDATA[Afficher un nom]]></li><li group="locale_en_US_204" name="L_P_execute_script"><![CDATA[Executer JavaScript]]></li><li group="locale_en_US_204" name="L_P_open_win"><![CDATA[Fenetre ouverte]]></li><li group="locale_en_US_204" name="L_P_sql"><![CDATA[Executez SQL]]></li><li group="locale_en_US_203" name="F_P_CUM"><![CDATA[Somme cumulative]]></li><li group="locale_en_US_203" name="F_RNK"><![CDATA[Rang]]></li><li group="locale_en_US_203" name="F_AVG"><![CDATA[Moyen]]></li><li group="locale_en_US_203" name="F_STOT"><![CDATA[Total]]></li><li group="locale_en_US_203" name="T_M_Measure"><![CDATA[Inscrivez-mesures]]></li><li group="locale_en_US_203" name="F_INC"><![CDATA[Incremental]]></li><li group="locale_en_US_203" name="F_P_TOT"><![CDATA[Pour cent du total]]></li><li group="locale_en_US_203" name="F_DIFF"><![CDATA[Difference]]></li><li group="locale_en_US_203" name="F_MIN"><![CDATA[Le minimum]]></li><li group="locale_en_US_203" name="L_R_ANAL_CUBE_L"><![CDATA[Nom Sujet]]></li><li group="locale_en_US_203" name="B_SEQUENCE"><![CDATA[Commande]]></li><li group="locale_en_US_203" name="T_SYS_RES"><![CDATA[Ressources systeme]]></li><li group="locale_en_US_202" name="L_ADD_VAR"><![CDATA[Ajouter une variable]]></li><li group="locale_en_US_202" name="L_V_DESC"><![CDATA[Editeur de variable dynamique]]></li><li group="locale_en_US_202" name="L_CR_TP_SEL"><![CDATA[Selectionner un article]]></li><li group="locale_en_US_202" name="L_RM_VAR"><![CDATA[Retirer variable]]></li><li group="locale_en_US_202" name="T_FEATURES"><![CDATA[Caracteristiques]]></li><li group="locale_en_US_202" name="D_BIGDATA"><![CDATA[Big Data]]></li><li group="locale_en_US_201" name="L_R_UPD_TGT"><![CDATA[Percer cible]]></li><li group="locale_en_US_201" name="L_REVISION"><![CDATA[Controle de version]]></li><li group="locale_en_US_201" name="B_OPT_LAYOUT"><![CDATA[Disposition]]></li><li group="locale_en_US_201" name="B_PATH"><![CDATA[Chemin]]></li><li group="locale_en_US_201" name="L_OPT_GRID"><![CDATA[Option de grille]]></li><li group="locale_en_US_201" name="B_SHEET_NAME"><![CDATA[Nom de la feuille]]></li><li group="locale_en_US_201" name="L_R_UT_DESC"><![CDATA[Lors de l'enregistrement d'un ou plusieurs, ne percez a selectionne.]]></li><li group="locale_en_US_201" name="L_ONLOAD_RUN"><![CDATA[Executer sur le chargement]]></li><li group="locale_en_US_201" name="L_R_CM_SHOWTAB"><![CDATA[Ouvrir dans un onglet]]></li><li group="locale_en_US_201" name="L_R_ANAL_CUBE"><![CDATA[Analyse Cube]]></li><li group="locale_en_US_201" name="L_FIXED_W"><![CDATA[Fixer Largeur]]></li><li group="locale_en_US_201" name="L_FIXED_H"><![CDATA[Fix Hauteur]]></li><li group="locale_en_US_201" name="L_SET_DEF"><![CDATA[L'utilisation par defaut]]></li><li group="locale_en_US_201" name="L_R_CMENU"><![CDATA[Cible de forage externe]]></li><li group="locale_en_US_201" name="B_SEL"><![CDATA[Selectionner]]></li><li group="locale_en_US_201" name="L_R_COLUMN_FIT"><![CDATA[Fit colonne au panneau]]></li><li group="locale_en_US_201" name="L_R_ANAL_CUBE_LB"><![CDATA[Cube]]></li><li group="locale_en_US_201" name="B_ADD"><![CDATA[Ajouter]]></li><li group="locale_en_US_201" name="L_R_RUN_PROP"><![CDATA[Proprietes d'execution]]></li><li group="locale_en_US_201" name="T_REVISION"><![CDATA[Controle de revision]]></li><li group="locale_en_US_201" name="B_REMOVE"><![CDATA[enlever]]></li><li group="locale_en_US_201" name="L_R_UT_DRILL"><![CDATA[Mise a jour Sheet]]></li><li group="locale_en_US_201" name="L_HIDE_TITLE"><![CDATA[Masquer le titre]]></li><li group="locale manager" name="L_LM_ADD"><![CDATA[Ajouter Country Code]]></li><li group="locale manager" name="L_LM_IMP"><![CDATA[Importation de donnees Locale]]></li><li group="locale manager" name="L_LM_EXP"><![CDATA[Export de donnees Locale]]></li><li group="locale manager" name="L_LM_LCS"><![CDATA[Ajouter Locale article]]></li><li group="locale manager" name="I_LOC_MGR"><![CDATA[Gestionnaire Locale]]></li><li group="formula" name="L_SYNTAX_FORMULA"><![CDATA[Syntaxe de la formule]]></li><li group="formula" name="L_FM_DISP1"><![CDATA[* Double champ de clic pour ajouter dans la fonction.]]></li><li group="formula" name="L_FM_DISP2"><![CDATA[* Faire glisser des elements ici pour definir cette mesure.]]></li><li group="filtereditor" name="L_OPERATOR"><![CDATA[Operateur]]></li><li group="filtereditor" name="L_VALUE_TYPE"><![CDATA[Type de valeur]]></li><li group="fileupload" name="L_SELECT_FILE"><![CDATA[Choisir le dossier...]]></li><li group="fileupload" name="L_MSG_TABNAME"><![CDATA[Type de texte de l'etiquette de donnees pour onglet dimension.]]></li><li group="fileupload" name="L_FILE_APPEND"><![CDATA[Append sur l'onglet courant]]></li><li group="fileupload" name="L_FILE_DELETE"><![CDATA[Remplacer les donnees existantes]]></li><li group="explorer" name="L_E_DEL"><![CDATA[Effacer]]></li><li group="explorer" name="B_MODI"><![CDATA[Modificateur]]></li><li group="explorer" name="L_C_CD"><![CDATA[Contenu supprime]]></li><li group="explorer" name="L_C_LC"><![CDATA[La plupart des contenus recents]]></li><li group="explorer" name="L_C_PR"><![CDATA[Privees matieres]]></li><li group="explorer" name="L_C_DC"><![CDATA[Sommaire supprimes]]></li><li group="explorer" name="L_C_AL"><![CDATA[Tous les contenus]]></li><li group="explorer" name="L_B_BW"><![CDATA[Bisiness workflow]]></li><li group="explorer" name="L_B_MVT"><![CDATA[Demenager a]]></li><li group="explorer" name="L_B_CM"><![CDATA[Metrics personnalises]]></li><li group="explorer" name="L_B_AC"><![CDATA[Analyse Cube]]></li><li group="explorer" name="B_LASTUPD"><![CDATA[Derniere mise a jour]]></li><li group="explorer" name="B_LOC"><![CDATA[Lieu]]></li><li group="explorer" name="B_OWNER"><![CDATA[Proprietaire]]></li><li group="explorer" name="L_E_CB"><![CDATA[Modifier Cube]]></li><li group="explorer" name="B_CR"><![CDATA[Creer ..]]></li><li group="explorer" name="L_C_MW"><![CDATA[Gerer l'espace de travail]]></li><li group="explorer" name="L_E_IT"><![CDATA[Modifier l'element]]></li><li group="explorer" name="L_RECOVER"><![CDATA[Recuperer]]></li><li group="explorer" name="L_C_FC"><![CDATA[Mes favoris]]></li><li group="explorer" name="L_B_JV"><![CDATA[Map / Reduce Java]]></li><li group="explorer" name="L_B_U"><![CDATA[Monter]]></li><li group="excelloader_option" name="T_LDATA_TITLE"><![CDATA[Data Option Local Cube]]></li><li group="excelloader" name="L_IMPORT_FILE"><![CDATA[Importer le fichier]]></li><li group="excelloader" name="L_GROUP_MEASURE"><![CDATA[Mesure de groupe]]></li><li group="excelloader" name="L_SAVE_EXCEL"><![CDATA[Enregistrer le contenu]]></li><li group="excelloader" name="L_DATA_TAB"><![CDATA[Telechargee donnees]]></li><li group="excelloader" name="L_SAVE_EXCEL_AS"><![CDATA[Enregistrer le contenu sous]]></li><li group="errors" name="E_PV_L"><![CDATA[Erreur de privilege sur le contenu: (@)]]></li><li group="dynfilter" name="M_SEL_ERR"><![CDATA[@ est necessaire. S'il vous plait selectionner la valeur]]></li><li group="dynfilter" name="L_DYN_SELECT"><![CDATA[Verifiez les valeurs]]></li><li group="dynfilter" name="T_DYN_SELECT"><![CDATA[Selectionner des valeurs ...]]></li><li group="docking" name="L_R_OPT_FILTER"><![CDATA[Options de filtrage]]></li><li group="dlgsheet" name="L_DISTINCT_QUERY"><![CDATA[Requete distincte]]></li><li group="dlgsheet" name="L_DRILLREPORT"><![CDATA[Utilisez pour une vue detaillee]]></li><li group="dlgsheet" name="L_CLOSEABLE"><![CDATA[Closable]]></li><li group="dlgsheet" name="L_FIXEDSIZE"><![CDATA[Mode de taille fixe]]></li><li group="dlgselectpool" name="T_SELECT_POOL"><![CDATA[Selectionnez Piscine]]></li><li group="dlgrwizard" name="T_R_WIZARD"><![CDATA[Assistant statistique R]]></li><li group="dlgrwizard" name="L_R_PARAM"><![CDATA[Les parametres R]]></li><li group="dlgpassword" name="L_PWD_OLD"><![CDATA[ancien mot de passe]]></li><li group="dlgpassword" name="L_PWD_LABEL"><![CDATA[Mot de passe securise]]></li><li group="dlgpassword" name="L_PWD_NEW"><![CDATA[nouveau mot de passe]]></li><li group="dlgpassword" name="L_PWD_CONFIRM"><![CDATA[Confirmer le nouveau mot de passe]]></li><li group="dlgobjectauth" name="L_AU_TITLE"><![CDATA[L'acces aux objets Ensemble pour devoir]]></li><li group="dlgobjectauth" name="L_AU_APPLY_SUB"><![CDATA[Appliquer tous les sous-dossier]]></li><li group="dlgmetriceditor" name="L_MC_ELEM_EDT"><![CDATA[Element Editor]]></li><li group="dlgmetaselect" name="L_SELECT_PATH"><![CDATA[Selectionnez le chemin pour creer]]></li><li group="dlgmetaselect" name="L_SELECT_ITEM"><![CDATA[Selectionnez l'option de continuer]]></li><li group="dlgmetaselect" name="L_TYPE_ITEM_NAME"><![CDATA[Set nom de l'element pour creer]]></li><li group="dlgmeasure" name="L_ME_DISP1"><![CDATA[* Double champ de clic pour ajouter dans la fonction]]></li><li group="dlgmeasure" name="L_TYPE"><![CDATA[Type]]></li><li group="dlgmakestyle" name="L_STYLENAME"><![CDATA[Nom du style]]></li><li group="dlgmakestyle" name="L_MAKESTYLE"><![CDATA[Definir un nouveau style]]></li><li group="dlgmakeitem" name="T_RENAME_ITEM"><![CDATA[Renommer l'element (@)]]></li><li group="dlgmakeitem" name="L_MAKEITEM"><![CDATA[Assurez-Point (@)]]></li><li group="dlgmakeitem" name="L_DESCRIPTION"><![CDATA[Description]]></li><li group="dlgmakeitem" name="L_ITEMNAME"><![CDATA[Nom de l'article]]></li><li group="dlgmakeitem" name="L_MAKEITEM_G"><![CDATA[Assurez-Point]]></li><li group="dlghighlight" name="T_HL_OPT"><![CDATA[Options de Faits saillants]]></li><li group="dlghighlight" name="L_TB_HL"><![CDATA[Config Highlight]]></li><li group="dlgexportoption" name="L_PG_RANGE"><![CDATA[Intervalle de pages]]></li><li group="dlgexportoption" name="L_SHOW_PAGENUMBER"><![CDATA[Afficher le numero de la page]]></li><li group="dlgexportoption" name="L_FOOTER"><![CDATA[Bas de page]]></li><li group="dlgexportoption" name="L_FONT_SELECT"><![CDATA[Selection de la police]]></li><li group="dlgexportoption" name="L_PG_DIRECTION"><![CDATA[Direction la page]]></li><li group="dlgexportoption" name="L_PG_SIZE"><![CDATA[Taille de la page]]></li><li group="dlgexportoption" name="L_PG_START"><![CDATA[Debut de la page]]></li><li group="dlgexportoption" name="L_ALL_DATA"><![CDATA[Toutes les donnees]]></li><li group="dlgexportoption" name="L_HORIZONTAL"><![CDATA[Horizontal]]></li><li group="dlgexportoption" name="L_VERTICAL"><![CDATA[Verticale]]></li><li group="dlgexportoption" name="L_SHOW_FILTER_INFO"><![CDATA[Afficher les informations de filtre]]></li><li group="dlgexportoption" name="L_REPEAT_HEADER"><![CDATA[Repetez-tete]]></li><li group="dlgexportoption" name="L_SCALE_DOWN"><![CDATA[Reduire si necessaire]]></li><li group="dlgdatemetric" name="T_DM"><![CDATA[DateMetric editeur]]></li><li group="dlgdataeditor" name="L_MC_DATA_EDT"><![CDATA[Cube editeur de donnees]]></li><li group="dlgcustommetric" name="L_ADD_CONDITION"><![CDATA[Ajouter la condition]]></li><li group="dlgcustommetric" name="L_FEATURE"><![CDATA[Fonctionnalite]]></li><li group="dlgcustommetric" name="L_PREDEFINED_FIELD"><![CDATA[Un champ predefini]]></li><li group="dlgcustommetric" name="L_OTHER_VALUE"><![CDATA[Autre valeur]]></li><li group="dlgcustommetric" name="L_DATE_OPTION"><![CDATA[Date de Option]]></li><li group="dlgcustommetric" name="L_GROUP_LEVEL"><![CDATA[Au niveau du groupe]]></li><li group="dlgcustommetric" name="L_CUSTOM_FIELD"><![CDATA[Champ personnalise]]></li><li group="dlgcustommetric" name="L_ITEM"><![CDATA[Article]]></li><li group="dlgcustommetric" name="L_CUBE"><![CDATA[Cube]]></li><li group="dlgcustommetric" name="L_GROUP_FIELD"><![CDATA[Groupe terrain]]></li><li group="dlgcustommetric" name="L_CONDITION"><![CDATA[Condition]]></li><li group="dlgcustommetric" name="L_CM_DISP_1"><![CDATA[* Double champ de clic pour ajouter dans la fonction]]></li><li group="dlgcustommetric" name="L_CM_DISP_2"><![CDATA[* Glissez les articles ici pour definir cette mesure]]></li><li group="dlgcustommetric" name="L_SYNTAX"><![CDATA[Syntaxe]]></li><li group="dlgchartwizard" name="L_YAXIS_MIN"><![CDATA[Y-Axis Minimum]]></li><li group="dlgchartwizard" name="L_ADVANCED_OPTION"><![CDATA[Option avancee]]></li><li group="dlgchartwizard" name="L_CSTEP_5"><![CDATA[AxeY]]></li><li group="dlgchartwizard" name="L_YAXIS_FORMAT"><![CDATA[Le format de l'axe Y]]></li><li group="dlgchartwizard" name="L_TITLE"><![CDATA[Texte Titre]]></li><li group="dlgchartwizard" name="L_TITLE_POSITION"><![CDATA[Titre du poste]]></li><li group="dlgchartwizard" name="L_TITLE_OPTION"><![CDATA[Titre Cadre]]></li><li group="dlgchartwizard" name="L_TIME_OPTION"><![CDATA[Option de serie Temps]]></li><li group="dlgchartwizard" name="L_LABEL_DIST"><![CDATA[Etiquette Distance]]></li><li group="dlgchartwizard" name="L_CSTEP_3"><![CDATA[Legende]]></li><li group="dlgchartwizard" name="L_SWAP_AXIS"><![CDATA[Axe de swap]]></li><li group="dlgchartwizard" name="L_VIEW_OPTION"><![CDATA[Option Legend]]></li><li group="dlgchartwizard" name="L_LEGEND_POSITION"><![CDATA[Position de legende]]></li><li group="dlgchartwizard" name="L_CSTEP_1"><![CDATA[Graphique]]></li><li group="dlgchartwizard" name="L_CHART_GROUP"><![CDATA[Categorie Graphique]]></li><li group="dlgchartwizard" name="L_STACK_VALUE"><![CDATA[Valeur Stack]]></li><li group="dlgchartwizard" name="L_MAX_CHART_ELEMENT"><![CDATA[Elements de donnees]]></li><li group="dlgchartwizard" name="L_USE_FORMULA"><![CDATA[Montrer formule]]></li><li group="dlgchartwizard" name="L_INNER_RADIUS"><![CDATA[Rayon interne]]></li><li group="dlgchartwizard" name="L_SHOW_LEGEND"><![CDATA[Afficher la legende]]></li><li group="dlgchartwizard" name="L_YAXIS_MAX"><![CDATA[Y-Axis Maximum]]></li><li group="dlgchartwizard" name="L_DATA_OPTION"><![CDATA[Option Data]]></li><li group="dlgchartwizard" name="L_NUMBER_PRECISION"><![CDATA[Precision numerique]]></li><li group="dlgchartwizard" name="L_CHART_OPTION"><![CDATA[Data Option Pivot]]></li><li group="dlgchartwizard" name="L_CSTEP_4"><![CDATA[Surface]]></li><li group="dlgchartwizard" name="L_PIE_OPTION"><![CDATA[Option Pie]]></li><li group="dlgchartwizard" name="L_DUAL_AXIS"><![CDATA[Double axeY]]></li><li group="dlgchartwizard" name="L_ENABLE_DRILL"><![CDATA[Forer vers le bas]]></li><li group="dlgchartwizard" name="L_CSTEP_2"><![CDATA[Donnees]]></li><li group="dlgbizreport" name="L_ADD_REPORT"><![CDATA[Ajouter un rapport]]></li><li group="dlgbizreport" name="L_EDIT"><![CDATA[modifier]]></li><li group="dlgbizreport" name="L_REMOVE"><![CDATA[enlever]]></li><li group="dlgbizreport" name="L_REMOVE_SELECTED"><![CDATA[Enlever la selection]]></li><li group="dlgbizreport" name="L_EDIT_DATA"><![CDATA[Modifier les donnees]]></li><li group="dlgbizreport" name="L_FILTER"><![CDATA[Filtre]]></li><li group="dlgabout" name="L_CONTACT_CRED"><![CDATA[Copyright & copier ;;;;; 1996-2010 "+ $ ig / * appoption * /. Companyname +".]]></li><li group="dlgabout" name="L_CONTACT_HELP"><![CDATA[Pour le support s'il vous plait contacter]]></li><li group="desktopapp" name="L_DESKTOP_SETTING"><![CDATA[Reglage]]></li><li group="desktopapp" name="L_CHANGE_SETTING"><![CDATA[Modifier les parametres]]></li><li group="desktopapp" name="L_DESKTOP_LOGOUT"><![CDATA[Se deconnecter]]></li><li group="desktopapp" name="L_MENU_CUBE"><![CDATA[Analyse Cube]]></li><li group="desktopapp" name="L_T_LOGOUT"><![CDATA[Se deconnecter]]></li><li group="desktopapp" name="L_M_C_SAVE_DESKTOP"><![CDATA[Voulez-vous enregistrer des informations de bureau actuellement ouvert?]]></li><li group="desktopapp" name="L_DELETE_SHORTCUT"><![CDATA[Supprimer le raccourci]]></li><li group="desktopapp" name="L_M_C_LOGOUT"><![CDATA[S'il vous plait cliquez sur le bouton Oui pour vous deconnecter. Click pas de bouton pour annuler]]></li><li group="desktopapp" name="L_M_LOGOUT"><![CDATA[Etes-vous sur de vouloir vous deconnecter?]]></li><li group="desktopapp" name="L_MENU_REPORT"><![CDATA[Creer des rapports]]></li><li group="dashboardedit" name="L_LAYOUT_WIZARD"><![CDATA[Assistant Mise en forme]]></li><li group="dashboardedit" name="L_SCRIPT_WIZARD"><![CDATA[Assistant de script]]></li><li group="cube" name="L_MODEL_CREATE"><![CDATA[Creer Modele]]></li><li group="cube" name="M_BLANK"><![CDATA[Ajouter un item]]></li><li group="cube" name="L_CREATE_FOLDER"><![CDATA[Creer un dossier]]></li><li group="cube" name="L_SQL_PRE_PROC"><![CDATA[SQL Pre Processeur]]></li><li group="cube" name="L_ADD_JOIN"><![CDATA[Ajouter Inscrivez-]]></li><li group="cube" name="L_PRV_DATA"><![CDATA[Apercu des donnees]]></li><li group="cube" name="L_TABLE_FIELD"><![CDATA[Tableau DB]]></li><li group="cube" name="M_SAVED"><![CDATA[Enregistree avec succes contenu]]></li><li group="cube" name="L_REG_FOLDER"><![CDATA[Ajouter le dossier]]></li><li group="cube" name="M_DELETED"><![CDATA[Contenu reussi a retirer]]></li><li group="cube" name="L_CODE_FIELD"><![CDATA[Cartographie de code]]></li><li group="cube" name="L_REG_MEASURES"><![CDATA[Assurez-mesures]]></li><li group="cube" name="M_SAVED_FAV"><![CDATA[Ajoute a la liste des favoris]]></li><li group="cube" name="L_ERR_CUBE_ITEMS"><![CDATA[Articles depareilles ou erreur existent sur cube. Modifier et enregistrer cube de mettre a jour des informations incompatibles.]]></li><li group="cube" name="L_MODEL_EDIT"><![CDATA[Modifier Modele]]></li><li group="cube" name="L_SAVE_CUBE"><![CDATA[Sauvegarder Cube]]></li><li group="cube" name="M_SEL_MODEL"><![CDATA[Selectionnez le modele sur le bouton de la barre d'outils pour continuer cube design.]]></li><li group="cube" name="L_MODEL_SELECT"><![CDATA[Selectionnez un modele]]></li><li group="cube" name="L_REFRESH"><![CDATA[rafraichissement]]></li><li group="common" name="B_MOVE_DOWN"><![CDATA[Deplacer la ligne vers le bas]]></li><li group="common" name="B_CONFIG_ITEM"><![CDATA[Config article]]></li><li group="common" name="B_VALUE"><![CDATA[Valeur]]></li><li group="common" name="B_TYPE"><![CDATA[Type]]></li><li group="common" name="B_DAY"><![CDATA[jour]]></li><li group="common" name="B_TREEVIEW"><![CDATA[Arbre]]></li><li group="common" name="B_DELETE_ITEM"><![CDATA[Supprimer l'article]]></li><li group="common" name="B_QUARTER"><![CDATA[Trimestre]]></li><li group="common" name="B_PROPERTY"><![CDATA[Propriete]]></li><li group="common" name="B_PROC"><![CDATA[Traitement de la demande .. S'il vous plait patienter <br> un moment.]]></li><li group="common" name="B_PREVIOUS"><![CDATA[precedent]]></li><li group="common" name="B_SVN"><![CDATA[Versioning et recuperation]]></li><li group="common" name="I_EXP_SCH"><![CDATA[Contenu d'options de recherche]]></li><li group="common" name="B_DESC"><![CDATA[Description]]></li><li group="common" name="L_ALL_VALUE"><![CDATA[Tous Valeur]]></li><li group="common" name="B_CD_CHS"><![CDATA[Aimez-vous supprimer des elements verifies?]]></li><li group="common" name="L_SELECT_VALUE"><![CDATA[Selectionnez Valeur]]></li><li group="common" name="B_CD_MHS"><![CDATA[Aimez-vous les deplacer vers @ verifie?]]></li><li group="common" name="M_SEL_ITEM"><![CDATA[Selectionnez l'option pour continuer.]]></li><li group="common" name="M_LOCK_MSG"><![CDATA[Le contenu est verrouille par @ 1 a @ 2]]></li><li group="common" name="M_LOCK_TITLE"><![CDATA[Un contenu verrouille]]></li><li group="common" name="B_WEEK"><![CDATA[Semaine]]></li><li group="common" name="B_WEEKMONTH"><![CDATA[Semaine Mois]]></li><li group="common" name="B_WIZARD"><![CDATA[magicien]]></li><li group="common" name="B_SET_FILTER"><![CDATA[Definir le filtre]]></li><li group="common" name="B_CONFIRM"><![CDATA[Confirmer]]></li><li group="common" name="B_ORDER_DSC"><![CDATA[Ordre decroissant]]></li><li group="common" name="B_ORDER_ASC"><![CDATA[Ordre Croissant]]></li><li group="common" name="B_OPTION"><![CDATA[Option]]></li><li group="common" name="B_HOUR"><![CDATA[Heure]]></li><li group="common" name="B_REMOVE_PIVOT"><![CDATA[Retirer Pivot]]></li><li group="common" name="B_SHOW"><![CDATA[Afficher]]></li><li group="common" name="B_ENABLED"><![CDATA[Active]]></li><li group="common" name="B_NEXT"><![CDATA[la prochaine]]></li><li group="common" name="M_ERR_CDATA"><![CDATA[Erreur lors de la manipulation de donnees rapport personnalise]]></li><li group="common" name="M_ERR_NSAVE"><![CDATA[Besoin d'enregistrer le contenu!]]></li><li group="common" name="B_EXECUTE"><![CDATA[Executer]]></li><li group="common" name="B_NAME"><![CDATA[prenom]]></li><li group="common" name="B_MOVE_UP"><![CDATA[Deplacer la ligne jusqu'a]]></li><li group="common" name="B_HELP"><![CDATA[Aidez-moi]]></li><li group="common" name="B_MONTH"><![CDATA[Mois]]></li><li group="common" name="B_CLIPBOARD"><![CDATA[Copier dans le presse-papier]]></li><li group="common" name="B_MINUTE"><![CDATA[Minute]]></li><li group="common" name="B_AMPM"><![CDATA[MATIN APRES-MIDI]]></li><li group="common" name="M_ERR_CONNECT"><![CDATA[Impossible d'obtenir une connexion sur le serveur! Veuillez reessayer ulterieurement]]></li><li group="common" name="B_FAVORITES"><![CDATA[Favoris]]></li><li group="common" name="B_WORKSPACE"><![CDATA[Espace de travail]]></li><li group="common" name="B_SHOW_ALL"><![CDATA[Montre tout]]></li><li group="common" name="B_YEAR"><![CDATA[An]]></li><li group="common" name="B_FOLDER"><![CDATA[Dossier]]></li><li group="common" name="B_UNLOCK"><![CDATA[Ouvrir]]></li><li group="common" name="B_UNDO"><![CDATA[Annuler les changements]]></li><li group="common" name="B_BOTTOM"><![CDATA[Bas]]></li><li group="common" name="L_BTN_SEARCH"><![CDATA[Recherche]]></li><li group="common" name="B_CLOSE"><![CDATA[Pres]]></li><li group="common" name="B_SUCCESS"><![CDATA[Processus termine avec succes]]></li><li group="common" name="B_LOGIN"><![CDATA[S'identifier]]></li><li group="common" name="B_GENERAL"><![CDATA[General]]></li><li group="common" name="L_LOADING_REPORT"><![CDATA[Chargement...]]></li><li group="common" name="B_GO"><![CDATA[Aller]]></li><li group="common" name="B_COMBO_VAL"><![CDATA[Liste des valeurs]]></li><li group="common" name="B_SEARCH"><![CDATA[Recherche]]></li><li group="common" name="B_SCHEDULE"><![CDATA[Calendrier]]></li><li group="common" name="D_PRIVATECONTENT"><![CDATA[Document de systeme]]></li><li group="common" name="B_CUST_VAL"><![CDATA[Valeurs personnalisees]]></li><li group="common" name="B_PROC_CANCEL"><![CDATA[Annuler]]></li><li group="common" name="L_ERR_SAVE"><![CDATA[Pour continuer d'enregistrer du contenu avant.]]></li><li group="common" name="B_TOP"><![CDATA[Haut]]></li><li group="common" name="B_CUSTOM"><![CDATA[Coutume]]></li><li group="common" name="L_SAVE_CONTENT"><![CDATA[Enregistrer le contenu]]></li><li group="common" name="L_SAVE_CONTENTAS"><![CDATA[Enregistrer le contenu sous ...]]></li><li group="common" name="B_USER_DOC"><![CDATA[Instructions]]></li><li group="codemapping" name="L_T_LOOKUP"><![CDATA[Options Lookup]]></li><li group="codemapping" name="L_LOOKUP"><![CDATA[Metric Lookup]]></li><li group="codemapping" name="L_CLEAR_LOOKUP"><![CDATA[Retirer Lookup]]></li><li group="appmain" name="L_MGR_USER"><![CDATA[Gestionnaire de l'utilisateur]]></li><li group="appmain" name="L_MGR_DATABASE"><![CDATA[Gestionnaire de la base]]></li><li group="appmain" name="L_RELATION_VIEW"><![CDATA[Gestion des relations]]></li><li group="appmain" name="L_REG_DATABASE"><![CDATA[Inscription Base de donnees]]></li><li group="R report" name="S_MAX"><![CDATA[Maximum]]></li><li group="R report" name="S_VAR"><![CDATA[Variance]]></li><li group="R report" name="D_FOLDER"><![CDATA[Dossier]]></li><li group="R report" name="D_MDBCUBE"><![CDATA[MS Access Datacube]]></li><li group="R report" name="D_WORKSPACE"><![CDATA[Espace de travail]]></li><li group="R report" name="D_MOLAPCUBE"><![CDATA[MOLAP Cube]]></li><li group="R report" name="S_STDEV"><![CDATA[L'ecart-type]]></li><li group="R report" name="D_DASHBOARD"><![CDATA[Tableau de bord]]></li><li group="R report" name="S_AVG"><![CDATA[Moyen]]></li><li group="R report" name="S_STDERR"><![CDATA[Erreur standard]]></li><li group="R report" name="D_UIPAGE"><![CDATA[UI page]]></li><li group="R report" name="D_BIGDATAMODEL"><![CDATA[BigDataModel]]></li><li group="R report" name="D_FORMULA"><![CDATA[Formule]]></li><li group="R report" name="D_REPORT"><![CDATA[rapport]]></li><li group="R report" name="D_UDG"><![CDATA[User Group Defini]]></li><li group="R report" name="D_EXCELLOADER"><![CDATA[Local Cube de fichier]]></li><li group="R report" name="S_SKEW"><![CDATA[Asymetrie]]></li><li group="R report" name="D_COMPOSITEREPORT"><![CDATA[Rapport de synthese]]></li><li group="R report" name="D_NOSQLCUBE"><![CDATA[BigData Cube]]></li><li group="R report" name="S_BOTTOM"><![CDATA[Valeur de fond]]></li><li group="R report" name="S_SUM"><![CDATA[Recapitulatif]]></li><li group="R report" name="S_REL"><![CDATA[Fiable]]></li><li group="R report" name="S_TOP"><![CDATA[Haut valeur]]></li><li group="R report" name="D_GROUP"><![CDATA[Groupe]]></li><li group="R report" name="D_SQLCUBE"><![CDATA[SQL Cube]]></li><li group="R report" name="S_KURT"><![CDATA[Kurtosis]]></li><li group="R report" name="D_DATEMETRIC"><![CDATA[Date de Metric]]></li><li group="R report" name="D_JAVACLASS"><![CDATA[Java Class]]></li><li group="R report" name="S_MIN"><![CDATA[Le minimum]]></li><li group="R report" name="L_MIN_WIDTH"><![CDATA[Largeur min]]></li><li group="R report" name="L_MIN_HEIGHT"><![CDATA[Hauteur min]]></li><li group="R report" name="D_CHARTMEASURE"><![CDATA[Micro Graphique]]></li><li group="R report" name="D_GROUPFIELD"><![CDATA[Groupe defini de l'utilisateur]]></li><li group="R report" name="D_CUSTOMMETRIC"><![CDATA[Metric personnalises]]></li><li group="R report" name="D_METRIC"><![CDATA[Metrique]]></li><li group="R report" name="S_COUNT"><![CDATA[Compter]]></li><li group="R report" name="S_MEDIAN"><![CDATA[Median]]></li><li group="R report" name="S_RAN"><![CDATA[Gamme]]></li><li group="R report" name="D_CUBEMODEL"><![CDATA[ROLAP Cube Modele]]></li><li group="R report" name="D_MEASURE"><![CDATA[Mesure]]></li><li group="R report" name="D_CUBE"><![CDATA[ROLAP Cube]]></li></item>